loggext/__init__.py
loggext/decorators/__init__.py
loggext/decorators/_util.py
loggext/decorators/add_logging.py
loggext/extradata/__init__.py
loggext/extradata/_cls.py
loggext/extradata/hostname.py
loggext/extradata/program_name.py
loggext/extradata/short_name.py
loggext/extradata/username.py
loggext/formatting/__init__.py
loggext/formatting/builder.py
loggext/formatting/default_formats.py
loggext/handlers/__init__.py
loggext/handlers/colored.py
loggext/utility/__init__.py
loggext/utility/_color.py
loggext/utility/_impl.py
loggext-0.4.1.dist-info/LICENSE
loggext-0.4.1.dist-info/METADATA
loggext-0.4.1.dist-info/WHEEL
loggext-0.4.1.dist-info/top_level.txt
loggext-0.4.1.dist-info/RECORD
