Metadata-Version: 2.1
Name: loggext
Version: 0.4.1
Summary: logging extensions for pythons logging library
Home-page: https://github.com/utility-libraries/loggext-py
Author: PlayerG9
License: GPLv3
Project-URL: Author Github, https://github.com/PlayerG9
Project-URL: Homepage, https://github.com/utility-libraries/loggext-py
Project-URL: Documentation, https://utility-libraries.github.io/loggext-py/
Project-URL: Bug Tracker, https://github.com/PlayerG9/loggext-py/issues
Classifier: Intended Audience :: Developers
Classifier: License :: OSI Approved :: MIT License
Classifier: Natural Language :: English
Classifier: Operating System :: OS Independent
Classifier: Programming Language :: Python :: 3
Classifier: Programming Language :: Python :: 3 :: Only
Classifier: Programming Language :: Python :: 3.7
Classifier: Programming Language :: Python :: 3.8
Classifier: Programming Language :: Python :: 3.9
Classifier: Programming Language :: Python :: 3.10
Classifier: Programming Language :: Python :: 3.11
Classifier: Programming Language :: Python :: 3.12
Classifier: Programming Language :: Python :: 3.13
Classifier: Topic :: Utilities
Requires-Python: >=3.7
License-File: LICENSE
Provides-Extra: all
